global_exception_handler_func/__init__.py
global_exception_handler_func/main.py
global_exception_handler_func-1.4.dist-info/LICENSE.md
global_exception_handler_func-1.4.dist-info/METADATA
global_exception_handler_func-1.4.dist-info/WHEEL
global_exception_handler_func-1.4.dist-info/top_level.txt
global_exception_handler_func-1.4.dist-info/RECORD
