Metadata-Version: 2.2
Name: global_exception_handler_func
Version: 1.4
License-File: LICENSE.md
Dynamic: description
Dynamic: description-content-type
